eggroll/__init__.py
eggroll/cli/__init__.py
eggroll/cli/eggroll.py
eggroll/cli/commands/__init__.py
eggroll/cli/commands/task.py
eggroll/cli/utils/__init__.py
eggroll/cli/utils/cli_args.py
eggroll/cli/utils/cli_utils.py
eggroll/computing/__init__.py
eggroll/computing/egg_pair/__init__.py
eggroll/computing/egg_pair/egg_pair.py
eggroll/computing/roll_pair/__init__.py
eggroll/computing/roll_pair/_gc.py
eggroll/computing/roll_pair/_roll_pair.py
eggroll/computing/roll_pair/_roll_pair_context.py
eggroll/computing/tasks/__init__.py
eggroll/computing/tasks/consts.py
eggroll/computing/tasks/job_util.py
eggroll/computing/tasks/shutil.py
eggroll/computing/tasks/submit_utils.py
eggroll/computing/tasks/impl/__init__.py
eggroll/computing/tasks/impl/_aggregate.py
eggroll/computing/tasks/impl/_binary_sorted_map_partitions_with_index.py
eggroll/computing/tasks/impl/_map_partitions_with_index.py
eggroll/computing/tasks/impl/_multiple_store.py
eggroll/computing/tasks/impl/_reduce.py
eggroll/computing/tasks/impl/_roll_site_ops.py
eggroll/computing/tasks/impl/_single_store.py
eggroll/computing/tasks/impl/_task.py
eggroll/computing/tasks/impl/_with_stores.py
eggroll/computing/tasks/store/__init__.py
eggroll/computing/tasks/store/_adapter.py
eggroll/computing/tasks/store/_format.py
eggroll/computing/tasks/store/_lmdb.py
eggroll/computing/tasks/store/_type.py
eggroll/computing/tasks/transfer/__init__.py
eggroll/computing/tasks/transfer/transfer_pair.py
eggroll/computing/tasks/transfer/transfer_service.py
eggroll/config/__init__.py
eggroll/config/__main__.py
eggroll/config/config.py
eggroll/config/defaults.py
eggroll/core/__init__.py
eggroll/core/command/__init__.py
eggroll/core/command/command_client.py
eggroll/core/command/command_router.py
eggroll/core/command/command_service.py
eggroll/core/command/command_status.py
eggroll/core/command/command_uri.py
eggroll/core/command/command_utils.py
eggroll/core/datastructure/__init__.py
eggroll/core/datastructure/broker.py
eggroll-3.0.0.dist-info/METADATA
eggroll-3.0.0.dist-info/WHEEL
eggroll-3.0.0.dist-info/entry_points.txt
eggroll-3.0.0.dist-info/top_level.txt
eggroll-3.0.0.dist-info/RECORD
